emailgenerator/__init__.py
emailgenerator/__main__.py
emailgenerator-0.1.2.dist-info/LICENSE
emailgenerator-0.1.2.dist-info/METADATA
emailgenerator-0.1.2.dist-info/WHEEL
emailgenerator-0.1.2.dist-info/entry_points.txt
emailgenerator-0.1.2.dist-info/top_level.txt
emailgenerator-0.1.2.dist-info/RECORD
